screwdriver.py
screwdriver-0.15.0.dist-info/LICENSE
screwdriver-0.15.0.dist-info/METADATA
screwdriver-0.15.0.dist-info/WHEEL
screwdriver-0.15.0.dist-info/top_level.txt
screwdriver-0.15.0.dist-info/RECORD
