Metadata-Version: 2.1
Name: screwdriver
Version: 0.15.0
Summary: Collection of random python tools and utilities
Author-email: Christopher Trudeau <ctrudeau+pypi@arsensa.com>
License: The MIT License (MIT)
Project-URL: Homepage, https://github.com/cltrudeau/screwdriver
Project-URL: Documentation, https://screwdriver.readthedocs.io
Keywords: tools
Classifier: Development Status :: 4 - Beta
Classifier: Intended Audience :: Developers
Classifier: License :: OSI Approved :: MIT License
Classifier: Operating System :: OS Independent
Classifier: Programming Language :: Python :: 3 :: Only
Classifier: Programming Language :: Python :: 3.9
Classifier: Programming Language :: Python :: 3.10
Classifier: Programming Language :: Python :: 3.11
Classifier: Programming Language :: Python :: 3.12
Classifier: Programming Language :: Python :: 3.13
Classifier: Topic :: Software Development :: Libraries :: Application Frameworks
Classifier: Topic :: Software Development :: Libraries :: Python Modules
Requires-Python: >=3.9
License-File: LICENSE
Provides-Extra: dev
Requires-Dist: build==1.2.2.post1; extra == "dev"
Requires-Dist: coverage==7.6.4; extra == "dev"
Requires-Dist: nox==2024.10.9; extra == "dev"
Requires-Dist: pudb==2024.1.3; extra == "dev"
Requires-Dist: pyflakes==3.2.0; extra == "dev"
Requires-Dist: setuptools==75.2.0; extra == "dev"
Requires-Dist: Sphinx==8.1.3; extra == "dev"
Requires-Dist: sphinx-rtd-theme==3.0.1; extra == "dev"
Requires-Dist: twine==5.1.1; extra == "dev"
Requires-Dist: waelstow==0.11.1; extra == "dev"
